topsis/__init__.py
topsis/topsis.py
topsis_3283-1.1.1.dist-info/LICENSE.txt
topsis_3283-1.1.1.dist-info/METADATA
topsis_3283-1.1.1.dist-info/WHEEL
topsis_3283-1.1.1.dist-info/entry_points.txt
topsis_3283-1.1.1.dist-info/top_level.txt
topsis_3283-1.1.1.dist-info/RECORD
