Metadata-Version: 2.1
Name: topsis-3283
Version: 1.1.1
Summary: topsis package for MCDM problems
Home-page: https://pypi.python.org/pypi/topsis-3283
Author: Katinder Kaur
Author-email: katinder08@gmail.com
License: UNKNOWN
Platform: UNKNOWN
Classifier: Programming Language :: Python :: 3
Classifier: Programming Language :: Python :: 3.6
Classifier: Programming Language :: Python :: 3.7
Classifier: License :: OSI Approved :: MIT License
Classifier: Operating System :: OS Independent
Requires-Python: >=3.6
